RyStats/common/__init__.py
RyStats/common/entropy.py
RyStats/common/hypersphere.py
RyStats/common/polychoric.py
RyStats/common/procrustes.py
RyStats/dimensionality/__init__.py
RyStats/dimensionality/map.py
RyStats/dimensionality/parallel_analysis.py
RyStats/factoranalysis/__init__.py
RyStats/factoranalysis/maximum_likelihood.py
RyStats/factoranalysis/minimum_rank.py
RyStats/factoranalysis/minimum_residual.py
RyStats/factoranalysis/paf.py
RyStats/factoranalysis/pca.py
RyStats/factoranalysis/rotation.py
RyStats/inferential/__init__.py
RyStats/inferential/correlation.py
RyStats/inferential/linear_regression.py
RyStats/inferential/logistic_regression.py
RyStats/inferential/oneway_anova.py
RyStats/inferential/post_hoc.py
RyStats/inferential/simple_mediation.py
RyStats/inferential/ttests.py
RyStats/inferential/twoway_anova.py
RyStats/plots/__init__.py
RyStats/plots/colormap.py
RyStats/plots/correlation_plots.py
RyStats/plots/loading_table.py
RyStats/plots/scree_plot.py
RyStats/survey/__init__.py
RyStats/survey/cronbach_alpha.py
RyStats/survey/mcdonald_omega.py
RyStats/survey/reverse.py
RyStats-0.5.0.dist-info/LICENSE
RyStats-0.5.0.dist-info/METADATA
RyStats-0.5.0.dist-info/WHEEL
RyStats-0.5.0.dist-info/top_level.txt
RyStats-0.5.0.dist-info/RECORD
