Metadata-Version: 2.1
Name: RyStats
Version: 0.5.0
Summary: Psychology Related Statistics in Python!
Home-page: https://github.com/eribean/RyStats
Author: Ryan C. Sanchez
Author-email: ryan.sanchez@gofactr.com
License: MIT
Keywords: Psychology,Psychometrics,Factor Analysis,Data Science,Logistic Regression,Linear Regression,Mediation,Statistics
Platform: UNKNOWN
Classifier: Development Status :: 3 - Alpha
Classifier: Intended Audience :: Science/Research
Classifier: Topic :: Scientific/Engineering
Classifier: License :: OSI Approved :: MIT License
Classifier: Programming Language :: Python :: 3.8
Classifier: Programming Language :: Python :: 3.9
License-File: LICENSE
Requires-Dist: numpy
Requires-Dist: scipy
Requires-Dist: bokeh
Requires-Dist: ipython
